activeledgerPythonSDK/__about__.py
activeledgerPythonSDK/__init__.py
activeledgerPythonSDK-2.0.0.dist-info/LICENSE
activeledgerPythonSDK-2.0.0.dist-info/METADATA
activeledgerPythonSDK-2.0.0.dist-info/WHEEL
activeledgerPythonSDK-2.0.0.dist-info/top_level.txt
activeledgerPythonSDK-2.0.0.dist-info/RECORD
