Metadata-Version: 2.1
Name: activeledgerPythonSDK
Version: 2.0.0
Summary: activeledgersdk is a package to use full functions of activeledger for Python developers
Home-page: http://www.activeledger.io
Author: activeledger
Author-email: infor@activeledger.io
License: BSD or Apache License, Version 2.0
Platform: UNKNOWN
